wafermap_clustering/wafermap_clustering.py
wafermap_clustering/configs/config.py
wafermap_clustering/libs/klarf_lib.py
wafermap_clustering/models/clustered_defect.py
wafermap_clustering/models/clustering_performance.py
wafermap_clustering/models/clustering_result.py
wafermap_clustering-0.3.21.dist-info/LICENSE.txt
wafermap_clustering-0.3.21.dist-info/METADATA
wafermap_clustering-0.3.21.dist-info/WHEEL
wafermap_clustering-0.3.21.dist-info/top_level.txt
wafermap_clustering-0.3.21.dist-info/RECORD
