Metadata-Version: 2.1
Name: wafermap-clustering
Version: 0.3.21
Summary: A project to apply clustering on wafermaps
Home-page: https://github.com/Impro02/wafermap-clustering
Download-URL: https://github.com/Impro02/wafermap-clustering/archive/refs/tags/0.3.21.tar.gz
Author: Maxime MARTIN
Author-email: maxime.martin02@hotmail.fr
License: MIT
Classifier: Development Status :: 3 - Alpha
Classifier: Intended Audience :: Developers
Classifier: License :: OSI Approved :: MIT License
Classifier: Programming Language :: Python :: 3
License-File: LICENSE.txt
Requires-Dist: klarf-reader
Requires-Dist: scikit-learn
Requires-Dist: setuptools
Requires-Dist: pydantic
